pyayay.cp310-win32.pyd
ayumi/LICENSE
ayumi/ayumi.c
ayumi/ayumi.h
utils/tools.h
pyayay-0.1.1.dist-info/LICENSE
pyayay-0.1.1.dist-info/METADATA
pyayay-0.1.1.dist-info/WHEEL
pyayay-0.1.1.dist-info/top_level.txt
pyayay-0.1.1.dist-info/RECORD
