Metadata-Version: 2.1
Name: pyayay
Version: 0.1.1
Summary: PyAYay is a Python extension wrapper for AY-3-8910 sound chip emulator
Author: Ruslan Grohovecki
Author-email: Ruslan Grokhovetskiy <ruslan.gr@gmail.com>, Peter Sovietov <peter@sovietov.com>
Project-URL: Homepage, https://github.com/ruguevara/pyayay
Project-URL: Issues, https://github.com/ruguevara/pyayay/issues
Classifier: Programming Language :: Python :: 3
Classifier: License :: OSI Approved :: MIT License
Classifier: Operating System :: OS Independent
Requires-Python: >=3.8
License-File: LICENSE
Requires-Dist: numpy
